README.rst
setup.cfg
setup.py
cbork2/__init__.py
cbork2/compat.py
cbork2/decoder.py
cbork2/encoder.py
cbork2/types.py
cbork2.egg-info/PKG-INFO
cbork2.egg-info/SOURCES.txt
cbork2.egg-info/dependency_links.txt
cbork2.egg-info/requires.txt
cbork2.egg-info/top_level.txt