Metadata-Version: 1.1
Name: cbork2
Version: 4.0.1
Summary: Pure Python CBOR (de)serializer with extensive tag support
Home-page: https://hydra.ecd.space/f/cbork2/
Author: Eduard Christian Dumitrescu
Author-email: eduard.c.dumitrescu@gmail.com
License: MIT
Keywords: serialization cbor
Platform: UNKNOWN
Classifier: Development Status :: 5 - Production/Stable
Classifier: Intended Audience :: Developers
Classifier: License :: OSI Approved :: MIT License
Classifier: Programming Language :: Python
Classifier: Programming Language :: Python :: 2.7
Classifier: Programming Language :: Python :: 3
Classifier: Programming Language :: Python :: 3.3
Classifier: Programming Language :: Python :: 3.4
Classifier: Programming Language :: Python :: 3.5
Classifier: Programming Language :: Python :: 3.6
